{
  "$schema": "https://developer.microsoft.com/json-schemas/fabric/item/report/definition/bookmark/1.4.0/schema.json",
  "displayName": "AllScoresDefault",
  "name": "112cba88d9e720670111",
  "options": {
    "targetVisualNames": []
  },
  "explorationState": {
    "version": "1.3",
    "activeSection": "f2725e76ad7640e2700b",
    "filters": {
      "byExpr": [
        {
          "name": "61c291ff699d48504d6c",
          "type": "Advanced",
          "filter": {
            "Version": 2,
            "From": [
              {
                "Name": "s",
                "Entity": "StudentInfo",
                "Type": 0
              }
            ],
            "Where": [
              {
                "Condition": {
                  "Not": {
                    "Expression": {
                      "Comparison": {
                        "ComparisonKind": 0,
                        "Left": {
                          "Column": {
                            "Expression": {
                              "SourceRef": {
                                "Source": "s"
                              }
                            },
                            "Property": "STUDENTS.LastFirst"
                          }
                        },
                        "Right": {
                          "Literal": {
                            "Value": "null"
                          }
                        }
                      }
                    }
                  }
                }
              }
            ]
          },
          "expression": {
            "Column": {
              "Expression": {
                "SourceRef": {
                  "Entity": "StudentInfo"
                }
              },
              "Property": "STUDENTS.LastFirst"
            }
          },
          "howCreated": 1
        }
      ]
    },
    "sections": {
      "f2725e76ad7640e2700b": {
        "visualContainers": {
          "1f6cc6df0bd15a89dcd5": {
            "filters": {
              "byExpr": [
                {
                  "name": "0b8f565294f0039d5169",
                  "type": "Advanced",
                  "expression": {
                    "Column": {
                      "Expression": {
                        "SourceRef": {
                          "Entity": "StudentInfo"
                        }
                      },
                      "Property": "ELLcode"
                    }
                  },
                  "howCreated": 0
                }
              ]
            },
            "singleVisual": {
              "visualType": "advancedSlicerVisual",
              "objects": {}
            }
          },
          "2435d6f3b224e69a5802": {
            "filters": {
              "byExpr": [
                {
                  "name": "b79713e0570930736a80",
                  "type": "Categorical",
                  "expression": {
                    "Column": {
                      "Expression": {
                        "SourceRef": {
                          "Entity": "BatchDownload"
                        }
                      },
                      "Property": "TotalScaleScoreColor"
                    }
                  },
                  "howCreated": 0
                },
                {
                  "name": "708710382e1e1830df9f",
                  "type": "Advanced",
                  "expression": {
                    "Aggregation": {
                      "Expression": {
                        "Column": {
                          "Expression": {
                            "SourceRef": {
                              "Entity": "BatchDownload"
                            }
                          },
                          "Property": "TotalScaleScoreColor"
                        }
                      },
                      "Function": 5
                    }
                  },
                  "howCreated": 0
                }
              ]
            },
            "singleVisual": {
              "visualType": "clusteredColumnChart",
              "objects": {},
              "orderBy": [
                {
                  "Direction": 2,
                  "Expression": {
                    "Column": {
                      "Expression": {
                        "SourceRef": {
                          "Entity": "BatchDownload"
                        }
                      },
                      "Property": "TotalScaleScoreColor"
                    }
                  }
                }
              ],
              "activeProjections": {
                "Category": [
                  {
                    "Column": {
                      "Expression": {
                        "SourceRef": {
                          "Entity": "BatchDownload"
                        }
                      },
                      "Property": "TotalScaleScoreColor"
                    }
                  }
                ]
              }
            }
          },
          "2b704d08089778cc7a6e": {
            "filters": {
              "byExpr": [
                {
                  "name": "e5d6b6eda1ed7e3adda8",
                  "type": "Advanced",
                  "filter": {
                    "Version": 2,
                    "From": [
                      {
                        "Name": "m",
                        "Entity": "MeasureTable",
                        "Type": 0
                      }
                    ],
                    "Where": [
                      {
                        "Condition": {
                          "Comparison": {
                            "ComparisonKind": 0,
                            "Left": {
                              "Measure": {
                                "Expression": {
                                  "SourceRef": {
                                    "Source": "m"
                                  }
                                },
                                "Property": "NameHasData"
                              }
                            },
                            "Right": {
                              "Literal": {
                                "Value": "1L"
                              }
                            }
                          }
                        }
                      }
                    ]
                  },
                  "expression": {
                    "Measure": {
                      "Expression": {
                        "SourceRef": {
                          "Entity": "MeasureTable"
                        }
                      },
                      "Property": "NameHasData"
                    }
                  },
                  "howCreated": 1
                },
                {
                  "name": "039ea591838811c131bc",
                  "type": "Categorical",
                  "expression": {
                    "Column": {
                      "Expression": {
                        "SourceRef": {
                          "Entity": "StudentInfo"
                        }
                      },
                      "Property": "STUDENTS.LastFirst"
                    }
                  },
                  "howCreated": 0
                }
              ]
            },
            "singleVisual": {
              "visualType": "slicer",
              "objects": {
                "merge": {
                  "data": [
                    {
                      "properties": {
                        "mode": {
                          "expr": {
                            "Literal": {
                              "Value": "'Dropdown'"
                            }
                          }
                        }
                      }
                    }
                  ]
                }
              },
              "activeProjections": {
                "Values": [
                  {
                    "Column": {
                      "Expression": {
                        "SourceRef": {
                          "Entity": "StudentInfo"
                        }
                      },
                      "Property": "STUDENTS.LastFirst"
                    }
                  }
                ]
              }
            }
          },
          "3645dea757033b5c2cbd": {
            "filters": {
              "byExpr": [
                {
                  "name": "9f7ce41f6b03e6d1c65d",
                  "type": "Categorical",
                  "expression": {
                    "Column": {
                      "Expression": {
                        "SourceRef": {
                          "Entity": "BatchDownload"
                        }
                      },
                      "Property": "Teacher"
                    }
                  },
                  "howCreated": 0
                }
              ]
            },
            "singleVisual": {
              "visualType": "slicer",
              "objects": {
                "merge": {
                  "data": [
                    {
                      "properties": {
                        "mode": {
                          "expr": {
                            "Literal": {
                              "Value": "'Dropdown'"
                            }
                          }
                        }
                      }
                    }
                  ]
                }
              },
              "activeProjections": {
                "Values": [
                  {
                    "Column": {
                      "Expression": {
                        "SourceRef": {
                          "Entity": "BatchDownload"
                        }
                      },
                      "Property": "Teacher"
                    }
                  }
                ]
              }
            }
          },
          "467f44f1e9dd23847e20": {
            "filters": {
              "byExpr": [
                {
                  "name": "c9ef3de76dcc5a460eae",
                  "type": "Categorical",
                  "expression": {
                    "Column": {
                      "Expression": {
                        "SourceRef": {
                          "Entity": "Counselors"
                        }
                      },
                      "Property": "Counselor"
                    }
                  },
                  "howCreated": 0
                }
              ]
            },
            "singleVisual": {
              "visualType": "slicer",
              "objects": {
                "merge": {
                  "data": [
                    {
                      "properties": {
                        "mode": {
                          "expr": {
                            "Literal": {
                              "Value": "'Dropdown'"
                            }
                          }
                        }
                      }
                    }
                  ]
                }
              },
              "activeProjections": {
                "Values": [
                  {
                    "Column": {
                      "Expression": {
                        "SourceRef": {
                          "Entity": "Counselors"
                        }
                      },
                      "Property": "Counselor"
                    }
                  }
                ]
              }
            }
          },
          "4d1a3aa0dd0850594833": {
            "singleVisual": {
              "visualType": "textbox",
              "objects": {}
            }
          },
          "51c4837ac18ba8707220": {
            "filters": {
              "byExpr": [
                {
                  "name": "1329ae71c60cb635cc64",
                  "type": "Advanced",
                  "expression": {
                    "Column": {
                      "Expression": {
                        "SourceRef": {
                          "Entity": "StudentInfo"
                        }
                      },
                      "Property": "IEP"
                    }
                  },
                  "howCreated": 0
                }
              ]
            },
            "singleVisual": {
              "visualType": "advancedSlicerVisual",
              "objects": {}
            }
          },
          "677901368ba8e008897e": {
            "singleVisual": {
              "visualType": "actionButton",
              "objects": {}
            }
          },
          "7f636b5926c777277222": {
            "filters": {
              "byExpr": [
                {
                  "name": "b10b3d44539d087e9930",
                  "type": "Categorical",
                  "expression": {
                    "Column": {
                      "Expression": {
                        "SourceRef": {
                          "Entity": "BatchDownload"
                        }
                      },
                      "Property": "Assessment Name"
                    }
                  },
                  "howCreated": 0
                }
              ]
            },
            "singleVisual": {
              "visualType": "slicer",
              "objects": {
                "merge": {
                  "data": [
                    {
                      "properties": {
                        "mode": {
                          "expr": {
                            "Literal": {
                              "Value": "'Dropdown'"
                            }
                          }
                        }
                      }
                    }
                  ]
                }
              },
              "activeProjections": {
                "Values": [
                  {
                    "Column": {
                      "Expression": {
                        "SourceRef": {
                          "Entity": "BatchDownload"
                        }
                      },
                      "Property": "Assessment Name"
                    }
                  }
                ]
              }
            }
          },
          "9eedd45126ad075b6050": {
            "filters": {
              "byExpr": [
                {
                  "name": "78ea4940be7c51a9a5ca",
                  "type": "Categorical",
                  "expression": {
                    "Column": {
                      "Expression": {
                        "SourceRef": {
                          "Entity": "StudentInfo"
                        }
                      },
                      "Property": "STUDENTS.LastFirst"
                    }
                  },
                  "howCreated": 0
                },
                {
                  "name": "25fdfb5cea7ed4531faa",
                  "type": "Advanced",
                  "expression": {
                    "Column": {
                      "Expression": {
                        "SourceRef": {
                          "Entity": "StudentInfo"
                        }
                      },
                      "Property": "STUDENTS.Grade_Level"
                    }
                  },
                  "howCreated": 0
                },
                {
                  "name": "636ec2574f91b791c419",
                  "type": "Categorical",
                  "expression": {
                    "Column": {
                      "Expression": {
                        "SourceRef": {
                          "Entity": "BatchDownload"
                        }
                      },
                      "Property": "Assessment Name"
                    }
                  },
                  "howCreated": 0
                },
                {
                  "name": "611b2ef2bc2010973275",
                  "type": "Advanced",
                  "expression": {
                    "Column": {
                      "Expression": {
                        "SourceRef": {
                          "Entity": "BatchDownload"
                        }
                      },
                      "Property": "Scale Score for DC 1"
                    }
                  },
                  "howCreated": 0
                },
                {
                  "name": "d6d2e1b8a6f687a3b927",
                  "type": "Advanced",
                  "expression": {
                    "Column": {
                      "Expression": {
                        "SourceRef": {
                          "Entity": "BatchDownload"
                        }
                      },
                      "Property": "Scale Score for DC 2"
                    }
                  },
                  "howCreated": 0
                },
                {
                  "name": "1c76f7b70f755a5b97b8",
                  "type": "Advanced",
                  "expression": {
                    "Column": {
                      "Expression": {
                        "SourceRef": {
                          "Entity": "BatchDownload"
                        }
                      },
                      "Property": "Scale Score for DC 3"
                    }
                  },
                  "howCreated": 0
                },
                {
                  "name": "9ea823ab4d670de5a6a2",
                  "type": "Advanced",
                  "expression": {
                    "Column": {
                      "Expression": {
                        "SourceRef": {
                          "Entity": "BatchDownload"
                        }
                      },
                      "Property": "Scale Score for DC 4"
                    }
                  },
                  "howCreated": 0
                },
                {
                  "name": "91d843ee7b4077464694",
                  "type": "Advanced",
                  "expression": {
                    "Column": {
                      "Expression": {
                        "SourceRef": {
                          "Entity": "BatchDownload"
                        }
                      },
                      "Property": "Scale Score for DC 5"
                    }
                  },
                  "howCreated": 0
                },
                {
                  "name": "8cc6b12934a96b1c0acd",
                  "type": "Advanced",
                  "expression": {
                    "Column": {
                      "Expression": {
                        "SourceRef": {
                          "Entity": "BatchDownload"
                        }
                      },
                      "Property": "Total Scale Score for Test"
                    }
                  },
                  "howCreated": 0
                },
                {
                  "name": "80c143546ab52231c369",
                  "type": "Categorical",
                  "expression": {
                    "Column": {
                      "Expression": {
                        "SourceRef": {
                          "Entity": "BatchDownload"
                        }
                      },
                      "Property": "Teacher"
                    }
                  },
                  "howCreated": 0
                },
                {
                  "name": "dd97b457edd79c4aebab",
                  "type": "Categorical",
                  "expression": {
                    "Column": {
                      "Expression": {
                        "SourceRef": {
                          "Entity": "BatchDownload"
                        }
                      },
                      "Property": "FinishedSameDay"
                    }
                  },
                  "howCreated": 0
                },
                {
                  "name": "524ed809f08969d3a25f",
                  "type": "Advanced",
                  "expression": {
                    "Column": {
                      "Expression": {
                        "SourceRef": {
                          "Entity": "BatchDownload"
                        }
                      },
                      "Property": "TestDurationMinutes"
                    }
                  },
                  "howCreated": 0
                },
                {
                  "name": "717e607f8f3b41e207f0",
                  "type": "Categorical",
                  "expression": {
                    "Column": {
                      "Expression": {
                        "SourceRef": {
                          "Entity": "BatchDownload"
                        }
                      },
                      "Property": "Starting Tested Date"
                    }
                  },
                  "howCreated": 0
                },
                {
                  "name": "6ff084b346f0e75b76ba",
                  "type": "Categorical",
                  "expression": {
                    "Column": {
                      "Expression": {
                        "SourceRef": {
                          "Entity": "BatchDownload"
                        }
                      },
                      "Property": "Starting Tested Time"
                    }
                  },
                  "howCreated": 0
                },
                {
                  "name": "f8f120a6316fc8056566",
                  "type": "Categorical",
                  "expression": {
                    "Column": {
                      "Expression": {
                        "SourceRef": {
                          "Entity": "BatchDownload"
                        }
                      },
                      "Property": "Ending Tested Date"
                    }
                  },
                  "howCreated": 0
                },
                {
                  "name": "1ce8704e9a7d1ffa6251",
                  "type": "Categorical",
                  "expression": {
                    "Column": {
                      "Expression": {
                        "SourceRef": {
                          "Entity": "BatchDownload"
                        }
                      },
                      "Property": "Ending Tested Time"
                    }
                  },
                  "howCreated": 0
                }
              ]
            },
            "singleVisual": {
              "visualType": "tableEx",
              "objects": {},
              "orderBy": [
                {
                  "Direction": 1,
                  "Expression": {
                    "Column": {
                      "Expression": {
                        "SourceRef": {
                          "Entity": "StudentInfo"
                        }
                      },
                      "Property": "STUDENTS.LastFirst"
                    }
                  }
                },
                {
                  "Direction": 1,
                  "Expression": {
                    "Column": {
                      "Expression": {
                        "SourceRef": {
                          "Entity": "BatchDownload"
                        }
                      },
                      "Property": "Assessment Name"
                    }
                  }
                }
              ]
            }
          },
          "a6e9420dc1d9e3000891": {
            "filters": {
              "byExpr": [
                {
                  "name": "3425eb161a52a09e29f9",
                  "type": "Categorical",
                  "expression": {
                    "Column": {
                      "Expression": {
                        "SourceRef": {
                          "Entity": "MentorsCMs"
                        }
                      },
                      "Property": "Mentor"
                    }
                  },
                  "howCreated": 0
                }
              ]
            },
            "singleVisual": {
              "visualType": "slicer",
              "objects": {
                "merge": {
                  "data": [
                    {
                      "properties": {
                        "mode": {
                          "expr": {
                            "Literal": {
                              "Value": "'Dropdown'"
                            }
                          }
                        }
                      }
                    }
                  ]
                }
              },
              "activeProjections": {
                "Values": [
                  {
                    "Column": {
                      "Expression": {
                        "SourceRef": {
                          "Entity": "MentorsCMs"
                        }
                      },
                      "Property": "Mentor"
                    }
                  }
                ]
              }
            }
          },
          "af7284526e2ee04004cc": {
            "filters": {
              "byExpr": [
                {
                  "name": "7ef405c2897e3426082a",
                  "type": "Advanced",
                  "filter": {
                    "Version": 2,
                    "From": [
                      {
                        "Name": "m",
                        "Entity": "MentorsCMs",
                        "Type": 0
                      }
                    ],
                    "Where": [
                      {
                        "Condition": {
                          "Not": {
                            "Expression": {
                              "Comparison": {
                                "ComparisonKind": 0,
                                "Left": {
                                  "Column": {
                                    "Expression": {
                                      "SourceRef": {
                                        "Source": "m"
                                      }
                                    },
                                    "Property": "Case Manager"
                                  }
                                },
                                "Right": {
                                  "Literal": {
                                    "Value": "null"
                                  }
                                }
                              }
                            }
                          }
                        }
                      }
                    ]
                  },
                  "expression": {
                    "Column": {
                      "Expression": {
                        "SourceRef": {
                          "Entity": "MentorsCMs"
                        }
                      },
                      "Property": "Case Manager"
                    }
                  },
                  "howCreated": 0
                }
              ]
            },
            "singleVisual": {
              "visualType": "slicer",
              "objects": {
                "merge": {
                  "data": [
                    {
                      "properties": {
                        "mode": {
                          "expr": {
                            "Literal": {
                              "Value": "'Dropdown'"
                            }
                          }
                        }
                      }
                    }
                  ]
                }
              },
              "activeProjections": {
                "Values": [
                  {
                    "Column": {
                      "Expression": {
                        "SourceRef": {
                          "Entity": "MentorsCMs"
                        }
                      },
                      "Property": "Case Manager"
                    }
                  }
                ]
              }
            }
          },
          "b1aeb9df03940e5a900a": {
            "filters": {
              "byExpr": [
                {
                  "name": "042ac1544043480e9ea4",
                  "type": "Advanced",
                  "expression": {
                    "Column": {
                      "Expression": {
                        "SourceRef": {
                          "Entity": "StudentInfo"
                        }
                      },
                      "Property": "Has504"
                    }
                  },
                  "howCreated": 0
                }
              ]
            },
            "singleVisual": {
              "visualType": "advancedSlicerVisual",
              "objects": {}
            }
          },
          "c29934f23665ca65d1cd": {
            "filters": {
              "byExpr": [
                {
                  "name": "66fa8744ee71fdb45cd7",
                  "type": "Advanced",
                  "expression": {
                    "Aggregation": {
                      "Expression": {
                        "Column": {
                          "Expression": {
                            "SourceRef": {
                              "Entity": "BatchDownload"
                            }
                          },
                          "Property": "Local ID"
                        }
                      },
                      "Function": 2
                    }
                  },
                  "howCreated": 0
                },
                {
                  "name": "a44b6149ecebc20ccbbb",
                  "type": "Advanced",
                  "expression": {
                    "Aggregation": {
                      "Expression": {
                        "Column": {
                          "Expression": {
                            "SourceRef": {
                              "Entity": "BatchDownload"
                            }
                          },
                          "Property": "TotalScaleScoreColor"
                        }
                      },
                      "Function": 5
                    }
                  },
                  "howCreated": 0
                },
                {
                  "name": "8ecb659b5dd5c1c1276d",
                  "type": "Advanced",
                  "expression": {
                    "Aggregation": {
                      "Expression": {
                        "Column": {
                          "Expression": {
                            "SourceRef": {
                              "Entity": "BatchDownload"
                            }
                          },
                          "Property": "Teacher"
                        }
                      },
                      "Function": 2
                    }
                  },
                  "howCreated": 0
                }
              ]
            },
            "singleVisual": {
              "visualType": "cardVisual",
              "objects": {},
              "orderBy": [
                {
                  "Direction": 2,
                  "Expression": {
                    "Aggregation": {
                      "Expression": {
                        "Column": {
                          "Expression": {
                            "SourceRef": {
                              "Entity": "BatchDownload"
                            }
                          },
                          "Property": "Local ID"
                        }
                      },
                      "Function": 2
                    }
                  }
                }
              ]
            }
          },
          "d13e5803a2b9e80deaca": {
            "filters": {
              "byExpr": [
                {
                  "name": "31560ffad0f9a2c78a12",
                  "type": "Categorical",
                  "expression": {
                    "Column": {
                      "Expression": {
                        "SourceRef": {
                          "Entity": "BatchDownload"
                        }
                      },
                      "Property": "Content Area"
                    }
                  },
                  "howCreated": 0
                }
              ]
            },
            "singleVisual": {
              "visualType": "slicer",
              "objects": {
                "merge": {
                  "data": [
                    {
                      "properties": {
                        "mode": {
                          "expr": {
                            "Literal": {
                              "Value": "'Dropdown'"
                            }
                          }
                        }
                      }
                    }
                  ]
                }
              },
              "activeProjections": {
                "Values": [
                  {
                    "Column": {
                      "Expression": {
                        "SourceRef": {
                          "Entity": "BatchDownload"
                        }
                      },
                      "Property": "Content Area"
                    }
                  }
                ]
              }
            }
          },
          "fada448743565044d058": {
            "filters": {
              "byExpr": [
                {
                  "name": "cf5ddf046bd7da61007f",
                  "type": "Categorical",
                  "expression": {
                    "Column": {
                      "Expression": {
                        "SourceRef": {
                          "Entity": "BatchDownload"
                        }
                      },
                      "Property": "Test Session Name"
                    }
                  },
                  "howCreated": 0
                }
              ]
            },
            "singleVisual": {
              "visualType": "slicer",
              "objects": {
                "merge": {
                  "data": [
                    {
                      "properties": {
                        "mode": {
                          "expr": {
                            "Literal": {
                              "Value": "'Dropdown'"
                            }
                          }
                        }
                      }
                    }
                  ]
                }
              },
              "activeProjections": {
                "Values": [
                  {
                    "Column": {
                      "Expression": {
                        "SourceRef": {
                          "Entity": "BatchDownload"
                        }
                      },
                      "Property": "Test Session Name"
                    }
                  }
                ]
              }
            }
          },
          "e93b86f7f30fcb472e73": {
            "filters": {
              "byExpr": [
                {
                  "name": "a82b4a4002239c588d5e",
                  "type": "Categorical",
                  "filter": {
                    "Version": 2,
                    "From": [
                      {
                        "Name": "b",
                        "Entity": "BatchDownload",
                        "Type": 0
                      }
                    ],
                    "Where": [
                      {
                        "Condition": {
                          "Not": {
                            "Expression": {
                              "In": {
                                "Expressions": [
                                  {
                                    "Column": {
                                      "Expression": {
                                        "SourceRef": {
                                          "Source": "b"
                                        }
                                      },
                                      "Property": "AHCCSsession"
                                    }
                                  }
                                ],
                                "Values": [
                                  [
                                    {
                                      "Literal": {
                                        "Value": "'Y'"
                                      }
                                    }
                                  ]
                                ]
                              }
                            }
                          }
                        }
                      }
                    ]
                  },
                  "expression": {
                    "Column": {
                      "Expression": {
                        "SourceRef": {
                          "Entity": "BatchDownload"
                        }
                      },
                      "Property": "AHCCSsession"
                    }
                  },
                  "howCreated": 0
                }
              ]
            },
            "singleVisual": {
              "visualType": "slicer",
              "objects": {
                "merge": {
                  "data": [
                    {
                      "properties": {
                        "mode": {
                          "expr": {
                            "Literal": {
                              "Value": "'Dropdown'"
                            }
                          }
                        }
                      }
                    }
                  ]
                }
              },
              "activeProjections": {
                "Values": [
                  {
                    "Column": {
                      "Expression": {
                        "SourceRef": {
                          "Entity": "BatchDownload"
                        }
                      },
                      "Property": "AHCCSsession"
                    }
                  }
                ]
              }
            }
          },
          "e632e4aeafe04f21781d": {
            "filters": {
              "byExpr": [
                {
                  "name": "15322bb011549e1c6d02",
                  "type": "Categorical",
                  "filter": {
                    "Version": 2,
                    "From": [
                      {
                        "Name": "c",
                        "Entity": "Courses",
                        "Type": 0
                      }
                    ],
                    "Where": [
                      {
                        "Condition": {
                          "Not": {
                            "Expression": {
                              "In": {
                                "Expressions": [
                                  {
                                    "Column": {
                                      "Expression": {
                                        "SourceRef": {
                                          "Source": "c"
                                        }
                                      },
                                      "Property": "TEACHERS.LASTFIRST"
                                    }
                                  }
                                ],
                                "Values": [
                                  [
                                    {
                                      "Literal": {
                                        "Value": "'Alderfer, Angela'"
                                      }
                                    }
                                  ],
                                  [
                                    {
                                      "Literal": {
                                        "Value": "'Facilitator, Staff'"
                                      }
                                    }
                                  ]
                                ]
                              }
                            }
                          }
                        }
                      }
                    ]
                  },
                  "expression": {
                    "Column": {
                      "Expression": {
                        "SourceRef": {
                          "Entity": "Courses"
                        }
                      },
                      "Property": "TEACHERS.LASTFIRST"
                    }
                  },
                  "howCreated": 0
                }
              ]
            },
            "singleVisual": {
              "visualType": "slicer",
              "objects": {
                "merge": {
                  "data": [
                    {
                      "properties": {
                        "mode": {
                          "expr": {
                            "Literal": {
                              "Value": "'Dropdown'"
                            }
                          }
                        }
                      }
                    }
                  ]
                }
              },
              "activeProjections": {
                "Values": [
                  {
                    "Column": {
                      "Expression": {
                        "SourceRef": {
                          "Entity": "Courses"
                        }
                      },
                      "Property": "TEACHERS.LASTFIRST"
                    }
                  }
                ]
              }
            }
          },
          "291b61affb29ff678e7f": {
            "filters": {
              "byExpr": [
                {
                  "name": "15322bb011549e1c6d02",
                  "type": "Categorical",
                  "filter": {
                    "Version": 2,
                    "From": [
                      {
                        "Name": "c",
                        "Entity": "Courses",
                        "Type": 0
                      }
                    ],
                    "Where": [
                      {
                        "Condition": {
                          "Not": {
                            "Expression": {
                              "In": {
                                "Expressions": [
                                  {
                                    "Column": {
                                      "Expression": {
                                        "SourceRef": {
                                          "Source": "c"
                                        }
                                      },
                                      "Property": "TEACHERS.LASTFIRST"
                                    }
                                  }
                                ],
                                "Values": [
                                  [
                                    {
                                      "Literal": {
                                        "Value": "'Alderfer, Angela'"
                                      }
                                    }
                                  ],
                                  [
                                    {
                                      "Literal": {
                                        "Value": "'Facilitator, Staff'"
                                      }
                                    }
                                  ]
                                ]
                              }
                            }
                          }
                        }
                      }
                    ]
                  },
                  "expression": {
                    "Column": {
                      "Expression": {
                        "SourceRef": {
                          "Entity": "Courses"
                        }
                      },
                      "Property": "TEACHERS.LASTFIRST"
                    }
                  },
                  "howCreated": 1
                },
                {
                  "name": "5b907707a9ae5d048dcf",
                  "type": "Categorical",
                  "expression": {
                    "Column": {
                      "Expression": {
                        "SourceRef": {
                          "Entity": "Courses"
                        }
                      },
                      "Property": "COURSES.COURSE_NAME"
                    }
                  },
                  "howCreated": 0
                }
              ]
            },
            "singleVisual": {
              "visualType": "slicer",
              "objects": {
                "merge": {
                  "data": [
                    {
                      "properties": {
                        "mode": {
                          "expr": {
                            "Literal": {
                              "Value": "'Dropdown'"
                            }
                          }
                        }
                      }
                    }
                  ]
                }
              },
              "activeProjections": {
                "Values": [
                  {
                    "Column": {
                      "Expression": {
                        "SourceRef": {
                          "Entity": "Courses"
                        }
                      },
                      "Property": "COURSES.COURSE_NAME"
                    }
                  }
                ]
              }
            }
          }
        }
      }
    },
    "objects": {
      "merge": {
        "outspacePane": [
          {
            "properties": {
              "expanded": {
                "expr": {
                  "Literal": {
                    "Value": "false"
                  }
                }
              }
            }
          }
        ]
      }
    }
  }
}